{
  "case_info": {
    "case_name": "case_21_pipe_flow",
    "book": "明渠水力学",
    "generated_at": "2025-11-14T09:05:28.584271",
    "version": "1.0"
  },
  "parameters": {
    "simulation_time": 10.0,
    "time_step": 0.01,
    "iterations": 1000
  },
  "results": {
    "success": true,
    "execution_time_ms": 364.92,
    "memory_usage_mb": 93.32,
    "flow_rate_m3s": 3.83,
    "water_level_m": 3.76,
    "velocity_ms": 0.87,
    "gate_opening_percent": 72.7,
    "data_points": [
      {
        "time": 0.0,
        "flow_rate": 5.82,
        "water_level": 2.71,
        "velocity": 1.03
      },
      {
        "time": 1.0,
        "flow_rate": 5.1,
        "water_level": 3.34,
        "velocity": 1.32
      },
      {
        "time": 2.0,
        "flow_rate": 5.13,
        "water_level": 3.03,
        "velocity": 1.01
      },
      {
        "time": 3.0,
        "flow_rate": 5.49,
        "water_level": 3.19,
        "velocity": 1.39
      },
      {
        "time": 4.0,
        "flow_rate": 4.11,
        "water_level": 3.4,
        "velocity": 1.26
      },
      {
        "time": 5.0,
        "flow_rate": 5.84,
        "water_level": 3.24,
        "velocity": 1.13
      },
      {
        "time": 6.0,
        "flow_rate": 5.51,
        "water_level": 2.91,
        "velocity": 1.11
      },
      {
        "time": 7.0,
        "flow_rate": 4.56,
        "water_level": 2.6,
        "velocity": 1.02
      },
      {
        "time": 8.0,
        "flow_rate": 5.45,
        "water_level": 2.92,
        "velocity": 1.13
      },
      {
        "time": 9.0,
        "flow_rate": 5.53,
        "water_level": 3.2,
        "velocity": 1.4
      },
      {
        "time": 10.0,
        "flow_rate": 4.75,
        "water_level": 2.97,
        "velocity": 1.3
      }
    ]
  }
}