{
  "case_info": {
    "case_name": "case_30_constructed_wetland",
    "book": "生态水力学",
    "generated_at": "2025-11-14T09:05:28.546167",
    "version": "1.0"
  },
  "parameters": {
    "simulation_time": 10.0,
    "time_step": 0.01,
    "iterations": 1000
  },
  "results": {
    "success": true,
    "execution_time_ms": 330.71,
    "memory_usage_mb": 48.2,
    "flow_rate_m3s": 5.13,
    "water_level_m": 3.88,
    "velocity_ms": 1.43,
    "gate_opening_percent": 75.0,
    "data_points": [
      {
        "time": 0.0,
        "flow_rate": 5.34,
        "water_level": 2.69,
        "velocity": 1.32
      },
      {
        "time": 1.0,
        "flow_rate": 4.05,
        "water_level": 2.99,
        "velocity": 1.31
      },
      {
        "time": 2.0,
        "flow_rate": 4.04,
        "water_level": 2.95,
        "velocity": 1.08
      },
      {
        "time": 3.0,
        "flow_rate": 4.48,
        "water_level": 3.01,
        "velocity": 1.25
      },
      {
        "time": 4.0,
        "flow_rate": 4.93,
        "water_level": 2.51,
        "velocity": 1.33
      },
      {
        "time": 5.0,
        "flow_rate": 5.15,
        "water_level": 2.94,
        "velocity": 1.12
      },
      {
        "time": 6.0,
        "flow_rate": 4.98,
        "water_level": 2.88,
        "velocity": 1.18
      },
      {
        "time": 7.0,
        "flow_rate": 5.04,
        "water_level": 3.0,
        "velocity": 1.32
      },
      {
        "time": 8.0,
        "flow_rate": 4.39,
        "water_level": 3.07,
        "velocity": 1.27
      },
      {
        "time": 9.0,
        "flow_rate": 4.72,
        "water_level": 3.35,
        "velocity": 1.24
      },
      {
        "time": 10.0,
        "flow_rate": 4.57,
        "water_level": 3.39,
        "velocity": 1.16
      }
    ]
  }
}